simple_db_connector/__init__.py
tests/__init__.py
tests/test_check_db_entry.py
tests/test_check_table.py
tests/test_convert_datatypes.py
tests/test_create_db_entry.py
tests/test_create_table.py
tests/test_get_db_entrys.py
tests/test_update_entry.py
simple_db_connector-0.1.3.dist-info/METADATA
simple_db_connector-0.1.3.dist-info/WHEEL
simple_db_connector-0.1.3.dist-info/top_level.txt
simple_db_connector-0.1.3.dist-info/RECORD
